build_install_wheels.py
build_install_wheels-0.2.0.dist-info/LICENSE
build_install_wheels-0.2.0.dist-info/WHEEL
build_install_wheels-0.2.0.dist-info/METADATA
build_install_wheels-0.2.0.dist-info/RECORD
