Metadata-Version: 2.1
Name: build_install_wheels
Version: 0.2.0
Summary: Build or install wheel packages for passing customize code between modules
Home-page: https://github.com/alex1993/build_install_wheels
License: UNKNOWN
Author: xichen3
Author-email: xichen3@microsoft.com
Classifier: License :: OSI Approved :: MIT License
